gocept/form/README.txt
gocept/form/__init__.py
gocept/form/action.py
gocept/form/base.py
gocept/form/base.txt
gocept/form/configure.zcml
gocept/form/confirm-action.txt
gocept/form/constraint.py
gocept/form/destructive-action.txt
gocept/form/ftesting.zcml
gocept/form/grouped-form.pt
gocept/form/grouped.py
gocept/form/grouped.txt
gocept/form/grouped_form_macros.pt
gocept/form/i18n.py
gocept/form/interfaces.py
gocept/form/multiple-constraints.txt
gocept/form/pagelet.py
gocept/form/schema.py
gocept/form/tests.py
gocept/form/locales/de/LC_MESSAGES/gocept.form.mo
gocept/form/locales/de/LC_MESSAGES/gocept.form.po
gocept/form/resources/validation.js
gocept_form-0.9.0.dist-info/METADATA
gocept_form-0.9.0.dist-info/WHEEL
gocept_form-0.9.0.dist-info/top_level.txt
gocept_form-0.9.0.dist-info/RECORD
