Metadata-Version: 2.4
Name: gocept.form
Version: 0.9.0
Summary: Extensions for zope.formlib
Home-page: http://pypi.python.org/pypi/gocept.form
Author: Christian Zagrodnick
Author-email: cz@gocept.com
License: ZPL 2.1
Requires-Dist: zope.interface
Requires-Dist: zope.component
Requires-Dist: zope.contentprovider
Requires-Dist: zope.viewlet
Provides-Extra: test
Requires-Dist: zope.testbrowser; extra == "test"
Requires-Dist: zope.app.testing; extra == "test"
Requires-Dist: zope.app.zcmlfiles; extra == "test"
Requires-Dist: zope.viewlet!=3.4.1; extra == "test"
Requires-Dist: z3c.pagelet; extra == "test"
Provides-Extra: formlib
Requires-Dist: zope.browserpage; extra == "formlib"
Requires-Dist: zope.formlib; extra == "formlib"
Provides-Extra: z3cform
Requires-Dist: z3c.form; extra == "z3cform"
Requires-Dist: z3c.pagelet; extra == "z3cform"
Dynamic: author
Dynamic: author-email
Dynamic: description
Dynamic: home-page
Dynamic: license
Dynamic: provides-extra
Dynamic: requires-dist
Dynamic: summary
